{"v":"5.7.5","fr":100,"ip":0,"op":300,"w":1024,"h":420,"nm":"Comp 1","ddd":0,"assets":[],"layers":[{"ddd":0,"ind":1,"ty":4,"nm":"Shape Layer 7","sr":1,"ks":{"o":{"a":0,"k":100,"ix":2},"r":{"a":0,"k":0,"ix":2},"p":{"a":0,"k":[0,0],"ix":2},"a":{"a":0,"k":[0,0],"ix":2},"s":{"a":0,"k":[100,100],"ix":2}},"ao":0,"hd":false,"shapes":[{"ty":"gr","hd":false,"it":[{"ty":"rc","hd":false,"d":1,"s":{"a":1,"k":[{"t":86,"s":[20,24],"i":{"x":[1],"y":[1]},"o":{"x":[0],"y":[0]}},{"t":129,"s":[20,28],"i":{"x":[1],"y":[1]},"o":{"x":[0],"y":[0]}}],"ix":2},"p":{"a":0,"k":[0,0],"ix":2},"r":{"a":0,"k":0,"ix":2}},{"ty":"fl","c":{"a":0,"k":[0.8352941176470589,0,0],"ix":2},"o":{"a":1,"k":[{"t":0,"s":[0],"i":{"x":[1],"y":[1]},"o":{"x":[0],"y":[0]}},{"t":39,"s":[0],"i":{"x":[1],"y":[1]},"o":{"x":[0],"y":[0]}},{"t":86,"s":[100],"i":{"x":[0.8],"y":[1]},"o":{"x":[0.4],"y":[0]}},{"t":200,"s":[0],"i":{"x":[1],"y":[1]},"o":{"x":[0],"y":[0]}}],"ix":2},"r":1,"bm":0,"nm":"Fill 1","mn":"ADBE Vector Graphic - Fill","hd":false},{"ty":"tm","s":{"a":0,"k":0,"ix":2},"e":{"a":0,"k":100,"ix":2},"o":{"a":0,"k":0,"ix":2},"m":1,"hd":false},{"ty":"tr","hd":false,"p":{"a":1,"k":[{"t":0,"s":[527.8729963463674,317.63829307907906],"i":{"x":[0.8],"y":[1]},"o":{"x":[0.4],"y":[0]}},{"t":39,"s":[573.1695780072469,271.20345458689167],"i":{"x":[1],"y":[1]},"o":{"x":[0],"y":[0]},"ti":[-29.48804928502602,-6.788997350069508],"to":[31.43909517065015,-44.4345322544826]},{"t":86,"s":[730.7055316822552,195.09987895433534],"i":{"x":[1],"y":[1]},"o":{"x":[0.42],"y":[0]},"ti":[14.75020720958992,-49.80650035725387],"to":[34.61642570424476,-11.91735534921116]},{"t":200,"s":[821.1574097490358,271.20345458689167],"i":{"x":[1],"y":[1]},"o":{"x":[0],"y":[0]}}],"ix":2},"a":{"a":0,"k":[0,0],"ix":2},"s":{"a":0,"k":[100,100],"ix":2},"r":{"a":1,"k":[{"t":0,"s":[0],"i":{"x":[0.8],"y":[1]},"o":{"x":[0.4],"y":[0]}},{"t":86,"s":[60],"i":{"x":[0.8],"y":[1]},"o":{"x":[0.4],"y":[0]}},{"t":200,"s":[328.1121990495899],"i":{"x":[1],"y":[1]},"o":{"x":[0],"y":[0]}}],"ix":2},"o":{"a":0,"k":100,"ix":2},"sk":{"a":0,"k":0,"ix":2},"sa":{"a":0,"k":0,"ix":2}}]}],"ip":0,"op":300,"st":0,"bm":0},{"ddd":0,"ind":2,"ty":4,"nm":"Shape Layer 6","sr":1,"ks":{"o":{"a":0,"k":100,"ix":2},"r":{"a":0,"k":0,"ix":2},"p":{"a":0,"k":[0,0],"ix":2},"a":{"a":0,"k":[0,0],"ix":2},"s":{"a":0,"k":[100,100],"ix":2}},"ao":0,"hd":false,"shapes":[{"ty":"gr","hd":false,"it":[{"ty":"rc","hd":false,"d":1,"s":{"a":1,"k":[{"t":90,"s":[20,24],"i":{"x":[1],"y":[1]},"o":{"x":[0],"y":[0]}},{"t":129,"s":[20,28],"i":{"x":[1],"y":[1]},"o":{"x":[0],"y":[0]}}],"ix":2},"p":{"a":0,"k":[0,0],"ix":2},"r":{"a":0,"k":0,"ix":2}},{"ty":"fl","c":{"a":0,"k":[0.8352941176470589,0,0],"ix":2},"o":{"a":1,"k":[{"t":4,"s":[0],"i":{"x":[1],"y":[1]},"o":{"x":[0],"y":[0]}},{"t":43,"s":[0],"i":{"x":[1],"y":[1]},"o":{"x":[0],"y":[0]}},{"t":90,"s":[100],"i":{"x":[0.8],"y":[1]},"o":{"x":[0.4],"y":[0]}},{"t":204,"s":[0],"i":{"x":[1],"y":[1]},"o":{"x":[0],"y":[0]}}],"ix":2},"r":1,"bm":0,"nm":"Fill 1","mn":"ADBE Vector Graphic - Fill","hd":false},{"ty":"tm","s":{"a":0,"k":0,"ix":2},"e":{"a":0,"k":100,"ix":2},"o":{"a":0,"k":0,"ix":2},"m":1,"hd":false},{"ty":"tr","hd":false,"p":{"a":1,"k":[{"t":4,"s":[526.285341880623,318.32003968156744],"i":{"x":[0.8],"y":[1]},"o":{"x":[0.4],"y":[0]}},{"t":43,"s":[620.6557757007615,226.81217956542966],"i":{"x":[1],"y":[1]},"o":{"x":[0],"y":[0]},"ti":[-29.48804928502602,-6.788997350069508],"to":[31.43909517065015,-44.4345322544826]},{"t":90,"s":[802,113],"i":{"x":[1],"y":[1]},"o":{"x":[0.42],"y":[0]},"ti":[14.75020720958992,-49.80650035725387],"to":[34.61642570424476,-11.91735534921116]},{"t":204,"s":[812.4976787024236,222.81786269734468],"i":{"x":[1],"y":[1]},"o":{"x":[0],"y":[0]}}],"ix":2},"a":{"a":0,"k":[0,0],"ix":2},"s":{"a":0,"k":[100,100],"ix":2},"r":{"a":1,"k":[{"t":4,"s":[0],"i":{"x":[0.8],"y":[1]},"o":{"x":[0.4],"y":[0]}},{"t":90,"s":[60],"i":{"x":[0.8],"y":[1]},"o":{"x":[0.4],"y":[0]}},{"t":204,"s":[328.1121990495899],"i":{"x":[1],"y":[1]},"o":{"x":[0],"y":[0]}}],"ix":2},"o":{"a":0,"k":100,"ix":2},"sk":{"a":0,"k":0,"ix":2},"sa":{"a":0,"k":0,"ix":2}}]}],"ip":0,"op":300,"st":0,"bm":0},{"ddd":0,"ind":3,"ty":4,"nm":"Shape Layer 5","sr":1,"ks":{"o":{"a":0,"k":100,"ix":2},"r":{"a":0,"k":0,"ix":2},"p":{"a":0,"k":[0,0],"ix":2},"a":{"a":0,"k":[0,0],"ix":2},"s":{"a":0,"k":[100,100],"ix":2}},"ao":0,"hd":false,"shapes":[{"ty":"gr","hd":false,"it":[{"ty":"rc","hd":false,"d":1,"s":{"a":1,"k":[{"t":86,"s":[20,24],"i":{"x":[1],"y":[1]},"o":{"x":[0],"y":[0]}},{"t":129,"s":[20,28],"i":{"x":[1],"y":[1]},"o":{"x":[0],"y":[0]}}],"ix":2},"p":{"a":0,"k":[0,0],"ix":2},"r":{"a":0,"k":0,"ix":2}},{"ty":"fl","c":{"a":0,"k":[0.8352941176470589,0,0],"ix":2},"o":{"a":1,"k":[{"t":0,"s":[0],"i":{"x":[1],"y":[1]},"o":{"x":[0],"y":[0]}},{"t":39,"s":[0],"i":{"x":[1],"y":[1]},"o":{"x":[0],"y":[0]}},{"t":86,"s":[100],"i":{"x":[0.8],"y":[1]},"o":{"x":[0.4],"y":[0]}},{"t":200,"s":[0],"i":{"x":[1],"y":[1]},"o":{"x":[0],"y":[0]}}],"ix":2},"r":1,"bm":0,"nm":"Fill 1","mn":"ADBE Vector Graphic - Fill","hd":false},{"ty":"tm","s":{"a":0,"k":0,"ix":2},"e":{"a":0,"k":100,"ix":2},"o":{"a":0,"k":0,"ix":2},"m":1,"hd":false},{"ty":"tr","hd":false,"p":{"a":1,"k":[{"t":0,"s":[525.1327747317432,317.9824447525748],"i":{"x":[0.8],"y":[1]},"o":{"x":[0.4],"y":[0]}},{"t":39,"s":[433.6525774188376,222.48026776835195],"i":{"x":[1],"y":[1]},"o":{"x":[0],"y":[0]},"ti":[41.16610130502784,-21.49193994397785],"to":[-48.61190687578414,-74.12119919787523]},{"t":86,"s":[252.2168527482413,116.87257123514888],"i":{"x":[1],"y":[1]},"o":{"x":[0.42],"y":[0]},"ti":[14.75020720958986,-49.80650035725387],"to":[-33.54272650051183,19.6741488468297]},{"t":200,"s":[194.27939445006774,208.88987470194567],"i":{"x":[1],"y":[1]},"o":{"x":[0],"y":[0]}}],"ix":2},"a":{"a":0,"k":[0,0],"ix":2},"s":{"a":0,"k":[100,100],"ix":2},"r":{"a":1,"k":[{"t":0,"s":[0],"i":{"x":[0.8],"y":[1]},"o":{"x":[0.4],"y":[0]}},{"t":86,"s":[60],"i":{"x":[0.8],"y":[1]},"o":{"x":[0.4],"y":[0]}},{"t":200,"s":[328.1121990495899],"i":{"x":[1],"y":[1]},"o":{"x":[0],"y":[0]}}],"ix":2},"o":{"a":1,"k":[{"t":39,"s":[100],"i":{"x":[1],"y":[1]},"o":{"x":[0],"y":[0]}},{"t":86,"s":[60],"i":{"x":[1],"y":[1]},"o":{"x":[0],"y":[0]}}],"ix":2},"sk":{"a":0,"k":0,"ix":2},"sa":{"a":0,"k":0,"ix":2}}]}],"ip":0,"op":300,"st":0,"bm":0},{"ddd":0,"ind":4,"ty":4,"nm":"Shape Layer 9","sr":1,"ks":{"o":{"a":0,"k":100,"ix":2},"r":{"a":0,"k":0,"ix":2},"p":{"a":0,"k":[0,0],"ix":2},"a":{"a":0,"k":[0,0],"ix":2},"s":{"a":0,"k":[100,100],"ix":2}},"ao":0,"hd":false,"shapes":[{"ty":"gr","hd":false,"it":[{"ty":"rc","hd":false,"d":1,"s":{"a":1,"k":[{"t":86,"s":[20,24],"i":{"x":[1],"y":[1]},"o":{"x":[0],"y":[0]}},{"t":129,"s":[20,28],"i":{"x":[1],"y":[1]},"o":{"x":[0],"y":[0]}}],"ix":2},"p":{"a":0,"k":[0,0],"ix":2},"r":{"a":0,"k":0,"ix":2}},{"ty":"fl","c":{"a":0,"k":[0.8352941176470589,0,0],"ix":2},"o":{"a":1,"k":[{"t":4,"s":[0],"i":{"x":[1],"y":[1]},"o":{"x":[0],"y":[0]}},{"t":43,"s":[0],"i":{"x":[1],"y":[1]},"o":{"x":[0],"y":[0]}},{"t":86,"s":[60],"i":{"x":[0.8],"y":[1]},"o":{"x":[0.4],"y":[0]}},{"t":204,"s":[0],"i":{"x":[1],"y":[1]},"o":{"x":[0],"y":[0]}}],"ix":2},"r":1,"bm":0,"nm":"Fill 1","mn":"ADBE Vector Graphic - Fill","hd":false},{"ty":"tm","s":{"a":0,"k":0,"ix":2},"e":{"a":0,"k":100,"ix":2},"o":{"a":0,"k":0,"ix":2},"m":1,"hd":false},{"ty":"tr","hd":false,"p":{"a":1,"k":[{"t":4,"s":[525.0782960552507,330.85382480461544],"i":{"x":[0.8],"y":[1]},"o":{"x":[0.4],"y":[0]}},{"t":43,"s":[525.0782960552507,289.63037202013857],"i":{"x":[1],"y":[1]},"o":{"x":[0],"y":[0]},"ti":[-49.10323758204299,4.982000830291668],"to":[3.6013882275540254,-23.37043422637703]},{"t":86,"s":[598.8009933501129,132.01260737251957],"i":{"x":[1],"y":[1]},"o":{"x":[0.42],"y":[0]},"ti":[2.5069730570822912,-11.299632079301546],"to":[27.56490008618232,-1.9231475581378277]},{"t":204,"s":[629.2943924544148,214.33052424263676],"i":{"x":[1],"y":[1]},"o":{"x":[0],"y":[0]}}],"ix":2},"a":{"a":0,"k":[0,0],"ix":2},"s":{"a":0,"k":[100,100],"ix":2},"r":{"a":1,"k":[{"t":4,"s":[0],"i":{"x":[0.8],"y":[1]},"o":{"x":[0.4],"y":[0]}},{"t":43,"s":[21.781297968633865],"i":{"x":[1],"y":[1]},"o":{"x":[0],"y":[0]}},{"t":86,"s":[120],"i":{"x":[0.8],"y":[1]},"o":{"x":[0.4],"y":[0]}},{"t":204,"s":[328.1121990495899],"i":{"x":[1],"y":[1]},"o":{"x":[0],"y":[0]}}],"ix":2},"o":{"a":0,"k":100,"ix":2},"sk":{"a":0,"k":0,"ix":2},"sa":{"a":0,"k":0,"ix":2}}]}],"ip":0,"op":300,"st":0,"bm":0},{"ddd":0,"ind":5,"ty":4,"nm":"Shape Layer 8","sr":1,"ks":{"o":{"a":0,"k":100,"ix":2},"r":{"a":0,"k":0,"ix":2},"p":{"a":0,"k":[0,0],"ix":2},"a":{"a":0,"k":[0,0],"ix":2},"s":{"a":0,"k":[100,100],"ix":2}},"ao":0,"hd":false,"shapes":[{"ty":"gr","hd":false,"it":[{"ty":"rc","hd":false,"d":1,"s":{"a":1,"k":[{"t":86,"s":[20,24],"i":{"x":[1],"y":[1]},"o":{"x":[0],"y":[0]}},{"t":129,"s":[20,28],"i":{"x":[1],"y":[1]},"o":{"x":[0],"y":[0]}}],"ix":2},"p":{"a":0,"k":[0,0],"ix":2},"r":{"a":0,"k":0,"ix":2}},{"ty":"fl","c":{"a":0,"k":[0.8352941176470589,0,0],"ix":2},"o":{"a":1,"k":[{"t":4,"s":[0],"i":{"x":[1],"y":[1]},"o":{"x":[0],"y":[0]}},{"t":43,"s":[0],"i":{"x":[1],"y":[1]},"o":{"x":[0],"y":[0]}},{"t":86,"s":[100],"i":{"x":[0.8],"y":[1]},"o":{"x":[0.4],"y":[0]}},{"t":204,"s":[0],"i":{"x":[1],"y":[1]},"o":{"x":[0],"y":[0]}}],"ix":2},"r":1,"bm":0,"nm":"Fill 1","mn":"ADBE Vector Graphic - Fill","hd":false},{"ty":"tm","s":{"a":0,"k":0,"ix":2},"e":{"a":0,"k":100,"ix":2},"o":{"a":0,"k":0,"ix":2},"m":1,"hd":false},{"ty":"tr","hd":false,"p":{"a":1,"k":[{"t":4,"s":[559.6824217330302,319.2761927155233],"i":{"x":[0.8],"y":[1]},"o":{"x":[0.4],"y":[0]}},{"t":43,"s":[559.6824217330302,262.49581668403016],"i":{"x":[1],"y":[1]},"o":{"x":[0],"y":[0]},"ti":[48.255143422073274,3.658621262375334],"to":[3.6013882275540254,-23.37043422637703]},{"t":86,"s":[506.2497225077341,68.01332800096311],"i":{"x":[1],"y":[1]},"o":{"x":[0.42],"y":[0]},"ti":[14.750207209589917,-49.80650035725387],"to":[-24.182913315802693,-1.4697367367663219]},{"t":204,"s":[450.21873941787953,167.28859655565066],"i":{"x":[1],"y":[1]},"o":{"x":[0],"y":[0]}}],"ix":2},"a":{"a":0,"k":[0,0],"ix":2},"s":{"a":0,"k":[100,100],"ix":2},"r":{"a":1,"k":[{"t":4,"s":[0],"i":{"x":[0.8],"y":[1]},"o":{"x":[0.4],"y":[0]}},{"t":43,"s":[21.781297968633865],"i":{"x":[1],"y":[1]},"o":{"x":[0],"y":[0]}},{"t":86,"s":[120],"i":{"x":[0.8],"y":[1]},"o":{"x":[0.4],"y":[0]}},{"t":204,"s":[328.1121990495899],"i":{"x":[1],"y":[1]},"o":{"x":[0],"y":[0]}}],"ix":2},"o":{"a":0,"k":100,"ix":2},"sk":{"a":0,"k":0,"ix":2},"sa":{"a":0,"k":0,"ix":2}}]}],"ip":0,"op":300,"st":0,"bm":0},{"ddd":0,"ind":6,"ty":4,"nm":"Shape Layer 4","sr":1,"ks":{"o":{"a":0,"k":100,"ix":2},"r":{"a":0,"k":0,"ix":2},"p":{"a":0,"k":[0,0],"ix":2},"a":{"a":0,"k":[0,0],"ix":2},"s":{"a":0,"k":[100,100],"ix":2}},"ao":0,"hd":false,"shapes":[{"ty":"gr","hd":false,"it":[{"ty":"rc","hd":false,"d":1,"s":{"a":1,"k":[{"t":86,"s":[20,24],"i":{"x":[1],"y":[1]},"o":{"x":[0],"y":[0]}},{"t":129,"s":[20,28],"i":{"x":[1],"y":[1]},"o":{"x":[0],"y":[0]}}],"ix":2},"p":{"a":0,"k":[0,0],"ix":2},"r":{"a":0,"k":0,"ix":2}},{"ty":"fl","c":{"a":0,"k":[0.8352941176470589,0,0],"ix":2},"o":{"a":1,"k":[{"t":0,"s":[0],"i":{"x":[1],"y":[1]},"o":{"x":[0],"y":[0]}},{"t":39,"s":[0],"i":{"x":[1],"y":[1]},"o":{"x":[0],"y":[0]}},{"t":86,"s":[100],"i":{"x":[0.8],"y":[1]},"o":{"x":[0.4],"y":[0]}},{"t":200,"s":[0],"i":{"x":[1],"y":[1]},"o":{"x":[0],"y":[0]}}],"ix":2},"r":1,"bm":0,"nm":"Fill 1","mn":"ADBE Vector Graphic - Fill","hd":false},{"ty":"tm","s":{"a":0,"k":0,"ix":2},"e":{"a":0,"k":100,"ix":2},"o":{"a":0,"k":0,"ix":2},"m":1,"hd":false},{"ty":"tr","hd":false,"p":{"a":1,"k":[{"t":0,"s":[561.4660551614993,317.5783772128245],"i":{"x":[0.8],"y":[1]},"o":{"x":[0.4],"y":[0]}},{"t":39,"s":[542.385351048106,263.8413297798184],"i":{"x":[1],"y":[1]},"o":{"x":[0],"y":[0]},"ti":[41.09691135101286,-5.137120196459705],"to":[-48.61190687578414,-74.12119919787523]},{"t":86,"s":[393.4090843166119,109.89225167088928],"i":{"x":[1],"y":[1]},"o":{"x":[0.42],"y":[0]},"ti":[14.75020720958986,-49.80650035725387],"to":[-79.20268692915795,20.71275533893731]},{"t":200,"s":[308.95804526893727,263.8413297798184],"i":{"x":[1],"y":[1]},"o":{"x":[0],"y":[0]}}],"ix":2},"a":{"a":0,"k":[0,0],"ix":2},"s":{"a":0,"k":[100,100],"ix":2},"r":{"a":1,"k":[{"t":0,"s":[0],"i":{"x":[0.8],"y":[1]},"o":{"x":[0.4],"y":[0]}},{"t":86,"s":[60],"i":{"x":[0.8],"y":[1]},"o":{"x":[0.4],"y":[0]}},{"t":200,"s":[328.1121990495899],"i":{"x":[1],"y":[1]},"o":{"x":[0],"y":[0]}}],"ix":2},"o":{"a":0,"k":100,"ix":2},"sk":{"a":0,"k":0,"ix":2},"sa":{"a":0,"k":0,"ix":2}}]}],"ip":0,"op":300,"st":0,"bm":0},{"ddd":0,"ind":7,"ty":4,"nm":"Shape Layer 3","sr":1,"ks":{"o":{"a":0,"k":100,"ix":2},"r":{"a":0,"k":0,"ix":2},"p":{"a":0,"k":[0,0],"ix":2},"a":{"a":0,"k":[0,0],"ix":2},"s":{"a":0,"k":[100,100],"ix":2}},"ao":0,"hd":false,"shapes":[{"ty":"gr","hd":false,"it":[{"ty":"rc","hd":false,"d":1,"s":{"a":1,"k":[{"t":90,"s":[20,24],"i":{"x":[1],"y":[1]},"o":{"x":[0],"y":[0]}},{"t":129,"s":[20,28],"i":{"x":[1],"y":[1]},"o":{"x":[0],"y":[0]}}],"ix":2},"p":{"a":0,"k":[0,0],"ix":2},"r":{"a":0,"k":0,"ix":2}},{"ty":"fl","c":{"a":0,"k":[0.8352941176470589,0,0],"ix":2},"o":{"a":1,"k":[{"t":4,"s":[0],"i":{"x":[1],"y":[1]},"o":{"x":[0],"y":[0]}},{"t":43,"s":[0],"i":{"x":[1],"y":[1]},"o":{"x":[0],"y":[0]}},{"t":90,"s":[100],"i":{"x":[0.8],"y":[1]},"o":{"x":[0.4],"y":[0]}},{"t":204,"s":[0],"i":{"x":[1],"y":[1]},"o":{"x":[0],"y":[0]}}],"ix":2},"r":1,"bm":0,"nm":"Fill 1","mn":"ADBE Vector Graphic - Fill","hd":false},{"ty":"tm","s":{"a":0,"k":0,"ix":2},"e":{"a":0,"k":100,"ix":2},"o":{"a":0,"k":0,"ix":2},"m":1,"hd":false},{"ty":"tr","hd":false,"p":{"a":1,"k":[{"t":4,"s":[540.9775882828728,527.7374060677193],"i":{"x":[0.8],"y":[1]},"o":{"x":[0.4],"y":[0]},"ti":[209.4545489686482,9.47707462728431e-7],"to":[6.784752937337885,-182.2275823234186]},{"t":90,"s":[227,223],"i":{"x":[1],"y":[1]},"o":{"x":[0.42],"y":[0]},"ti":[12.21818547100133,-93.3042426602471],"to":[-16.46841225127145,-7.916562883968936]},{"t":204,"s":[25.62017769008696,351.7374060677194],"i":{"x":[1],"y":[1]},"o":{"x":[0],"y":[0]}}],"ix":2},"a":{"a":0,"k":[0,0],"ix":2},"s":{"a":0,"k":[100,100],"ix":2},"r":{"a":1,"k":[{"t":4,"s":[0],"i":{"x":[0.8],"y":[1]},"o":{"x":[0.4],"y":[0]}},{"t":43,"s":[10],"i":{"x":[1],"y":[1]},"o":{"x":[0],"y":[0]}},{"t":90,"s":[20],"i":{"x":[0.8],"y":[1]},"o":{"x":[0.4],"y":[0]}},{"t":204,"s":[328.1121990495899],"i":{"x":[1],"y":[1]},"o":{"x":[0],"y":[0]}}],"ix":2},"o":{"a":0,"k":100,"ix":2},"sk":{"a":0,"k":0,"ix":2},"sa":{"a":0,"k":0,"ix":2}}]}],"ip":0,"op":300,"st":0,"bm":0},{"ddd":0,"ind":8,"ty":4,"nm":"Shape Layer 2","sr":1,"ks":{"o":{"a":0,"k":100,"ix":2},"r":{"a":0,"k":0,"ix":2},"p":{"a":0,"k":[0,0],"ix":2},"a":{"a":0,"k":[0,0],"ix":2},"s":{"a":0,"k":[100,100],"ix":2}},"ao":0,"hd":false,"shapes":[{"ty":"gr","hd":false,"it":[{"ty":"rc","hd":false,"d":1,"s":{"a":1,"k":[{"t":86,"s":[20,24],"i":{"x":[1],"y":[1]},"o":{"x":[0],"y":[0]}},{"t":129,"s":[20,28],"i":{"x":[1],"y":[1]},"o":{"x":[0],"y":[0]}}],"ix":2},"p":{"a":0,"k":[0,0],"ix":2},"r":{"a":0,"k":0,"ix":2}},{"ty":"fl","c":{"a":0,"k":[0.8352941176470589,0,0],"ix":2},"o":{"a":1,"k":[{"t":0,"s":[0],"i":{"x":[1],"y":[1]},"o":{"x":[0],"y":[0]}},{"t":39,"s":[0],"i":{"x":[1],"y":[1]},"o":{"x":[0],"y":[0]}},{"t":86,"s":[100],"i":{"x":[0.8],"y":[1]},"o":{"x":[0.4],"y":[0]}},{"t":200,"s":[0],"i":{"x":[1],"y":[1]},"o":{"x":[0],"y":[0]}}],"ix":2},"r":1,"bm":0,"nm":"Fill 1","mn":"ADBE Vector Graphic - Fill","hd":false},{"ty":"tm","s":{"a":0,"k":0,"ix":2},"e":{"a":0,"k":100,"ix":2},"o":{"a":0,"k":0,"ix":2},"m":1,"hd":false},{"ty":"tr","hd":false,"p":{"a":1,"k":[{"t":0,"s":[540.2422629148001,419.30217241610194],"i":{"x":[0.8],"y":[1]},"o":{"x":[0.4],"y":[0]},"ti":[-134.2217422470414,6.17110893810468],"to":[6.784752937337885,-182.2275823234186]},{"t":86,"s":[678.5893962499309,78.93853605246585],"i":{"x":[1],"y":[1]},"o":{"x":[0.42],"y":[0]},"ti":[1.050228860208335,-67.11421916767301],"to":[60.35350887355889,8.839385301731511]},{"t":200,"s":[730.9530326135672,239.5203542342839],"i":{"x":[1],"y":[1]},"o":{"x":[0],"y":[0]}}],"ix":2},"a":{"a":0,"k":[0,0],"ix":2},"s":{"a":0,"k":[100,100],"ix":2},"r":{"a":1,"k":[{"t":0,"s":[0],"i":{"x":[0.8],"y":[1]},"o":{"x":[0.4],"y":[0]}},{"t":39,"s":[20.055520042755358],"i":{"x":[1],"y":[1]},"o":{"x":[0],"y":[0]}},{"t":86,"s":[90],"i":{"x":[0.8],"y":[1]},"o":{"x":[0.4],"y":[0]}},{"t":200,"s":[328.1121990495899],"i":{"x":[1],"y":[1]},"o":{"x":[0],"y":[0]}}],"ix":2},"o":{"a":1,"k":[{"t":0,"s":[100],"i":{"x":[1],"y":[1]},"o":{"x":[0],"y":[0]}},{"t":15,"s":[80],"i":{"x":[1],"y":[1]},"o":{"x":[0],"y":[0]}},{"t":86,"s":[80],"i":{"x":[1],"y":[1]},"o":{"x":[0],"y":[0]}},{"t":129,"s":[100],"i":{"x":[1],"y":[1]},"o":{"x":[0],"y":[0]}}],"ix":2},"sk":{"a":0,"k":0,"ix":2},"sa":{"a":0,"k":0,"ix":2}}]}],"ip":0,"op":300,"st":0,"bm":0},{"ddd":0,"ind":9,"ty":4,"nm":"Shape Layer 1","sr":1,"ks":{"o":{"a":0,"k":100,"ix":2},"r":{"a":0,"k":0,"ix":2},"p":{"a":0,"k":[0,0],"ix":2},"a":{"a":0,"k":[0,0],"ix":2},"s":{"a":0,"k":[100,100],"ix":2}},"ao":0,"hd":false,"shapes":[{"ty":"gr","hd":false,"it":[{"ty":"rc","hd":false,"d":1,"s":{"a":1,"k":[{"t":90,"s":[20,24],"i":{"x":[1],"y":[1]},"o":{"x":[0],"y":[0]}},{"t":129,"s":[20,28],"i":{"x":[1],"y":[1]},"o":{"x":[0],"y":[0]}}],"ix":2},"p":{"a":0,"k":[0,0],"ix":2},"r":{"a":0,"k":0,"ix":2}},{"ty":"fl","c":{"a":0,"k":[0.8352941176470589,0,0],"ix":2},"o":{"a":1,"k":[{"t":4,"s":[0],"i":{"x":[1],"y":[1]},"o":{"x":[0],"y":[0]}},{"t":43,"s":[0],"i":{"x":[1],"y":[1]},"o":{"x":[0],"y":[0]}},{"t":90,"s":[100],"i":{"x":[0.8],"y":[1]},"o":{"x":[0.4],"y":[0]}},{"t":204,"s":[0],"i":{"x":[1],"y":[1]},"o":{"x":[0],"y":[0]}}],"ix":2},"r":1,"bm":0,"nm":"Fill 1","mn":"ADBE Vector Graphic - Fill","hd":false},{"ty":"tm","s":{"a":0,"k":0,"ix":2},"e":{"a":0,"k":100,"ix":2},"o":{"a":0,"k":0,"ix":2},"m":1,"hd":false},{"ty":"tr","hd":false,"p":{"a":1,"k":[{"t":4,"s":[541.5694799920223,529.9749037084387],"i":{"x":[0.8],"y":[1]},"o":{"x":[0.4],"y":[0]},"ti":[-174.8856842896802,-11.08808247767229],"to":[6.784752937337885,-182.2275823234186]},{"t":90,"s":[824,241],"i":{"x":[1],"y":[1]},"o":{"x":[0.42],"y":[0]},"ti":[1.050228860208335,-67.11421916767301],"to":[62.49613389213789,16.83919024960039]},{"t":204,"s":[928.6889892392737,353.9749037084386],"i":{"x":[1],"y":[1]},"o":{"x":[0],"y":[0]}}],"ix":2},"a":{"a":0,"k":[0,0],"ix":2},"s":{"a":0,"k":[100,100],"ix":2},"r":{"a":1,"k":[{"t":4,"s":[0],"i":{"x":[0.8],"y":[1]},"o":{"x":[0.4],"y":[0]}},{"t":90,"s":[60],"i":{"x":[0.8],"y":[1]},"o":{"x":[0.4],"y":[0]}},{"t":204,"s":[328.1121990495899],"i":{"x":[1],"y":[1]},"o":{"x":[0],"y":[0]}}],"ix":2},"o":{"a":0,"k":100,"ix":2},"sk":{"a":0,"k":0,"ix":2},"sa":{"a":0,"k":0,"ix":2}}]}],"ip":0,"op":300,"st":0,"bm":0}],"markers":[]}